src/__init__.py
src/options.py
src/bolts/__init__.py
src/bolts/attachments.py
src/bolts/json_maker.py
src/bolts/network.py
src/bolts/output_debug.py
src/bolts/output_elasticsearch.py
src/bolts/output_redis.py
src/bolts/phishing.py
src/bolts/raw_mail.py
src/bolts/tokenizer.py
src/bolts/urls.py
src/cli/__init__.py
src/cli/elasticsearch_queries.py
src/cli/spamscope_elasticsearch.py
src/cli/spamscope_topology.py
src/modules/__init__.py
src/modules/abstracts.py
src/modules/rabbitmq_client.py
src/modules/redis_client.py
src/modules/utils.py
src/modules/attachments/__init__.py
src/modules/attachments/attachments.py
src/modules/attachments/exceptions.py
src/modules/attachments/post_processing.py
src/modules/attachments/thug_analysis.py
src/modules/attachments/utils.py
src/modules/bitmap/__init__.py
src/modules/bitmap/bitmap.py
src/modules/bitmap/phishing_bitmap.py
src/modules/mails/__init__.py
src/modules/mails/dialects.py
src/modules/mails/phishing.py
src/modules/mails/post_processing.py
src/modules/mails/spamassassin_analysis.py
src/modules/networks/__init__.py
src/modules/networks/post_processing.py
src/spouts/__init__.py
src/spouts/files_mails.py
src/spouts/iter_files_mails.py
SpamScope-2.8.1.dist-info/LICENSE.txt
SpamScope-2.8.1.dist-info/METADATA
SpamScope-2.8.1.dist-info/NOTICE.txt
SpamScope-2.8.1.dist-info/WHEEL
SpamScope-2.8.1.dist-info/entry_points.txt
SpamScope-2.8.1.dist-info/top_level.txt
SpamScope-2.8.1.dist-info/RECORD
