Metadata-Version: 2.1
Name: SpamScope
Version: 2.8.1
Summary: Fast Advanced Spam Analysis tool
Home-page: https://github.com/SpamScope/spamscope
Author: Fedele Mantuano
Author-email: mantuano.fedele@gmail.com
Maintainer: Fedele Mantuano
Maintainer-email: mantuano.fedele@gmail.com
License: Apache License, Version 2.0
Keywords: spam,email,mail,apache,apache-storm
Platform: Linux
Classifier: License :: OSI Approved :: Apache Software License
Classifier: Intended Audience :: Developers
Classifier: Operating System :: OS Independent
Classifier: Programming Language :: Python
Classifier: Programming Language :: Python :: 2
Classifier: Programming Language :: Python :: 2.6
Classifier: Programming Language :: Python :: 2.7
Requires-Dist: PyYAML
Requires-Dist: astropy (==1.3.3)
Requires-Dist: backports.functools-lru-cache (>=1.3)
Requires-Dist: chainmap
Requires-Dist: lxml
Requires-Dist: mail-parser (>=3.9.0)
Requires-Dist: patool
Requires-Dist: pyparsing
Requires-Dist: python-magic
Requires-Dist: simplejson
Requires-Dist: six
Requires-Dist: ssdeep
Requires-Dist: streamparse (==3.15.1)
